LICENSE
README.md
setup.py
utracto/__init__.py
utracto/core.py
utracto/example.py
utracto/tracking.py
utracto/utils.py
utracto.egg-info/PKG-INFO
utracto.egg-info/SOURCES.txt
utracto.egg-info/dependency_links.txt
utracto.egg-info/requires.txt
utracto.egg-info/top_level.txt