Metadata-Version: 2.1
Name: utracto
Version: 0.0.9
Summary: Implementation of UTracto
Home-page: https://github.com/DelinteNicolas/UTracto
Author: Nicolas Delinte
Author-email: nicolas.delinte@uclouvain.be
License: GNU General Public License v3.0
Classifier: Development Status :: 4 - Beta
Classifier: Intended Audience :: Science/Research
Classifier: Natural Language :: English
Classifier: Programming Language :: Python
License-File: LICENSE
